referencesystem/BaseTransform.py
referencesystem/LinearTransform.py
referencesystem/Parametrization.py
referencesystem/SysReference.py
referencesystem/__init__.py
referencesystem/helpers.py
ReferenceSystem_busnellistefano-1.0.0.dist-info/METADATA
ReferenceSystem_busnellistefano-1.0.0.dist-info/WHEEL
ReferenceSystem_busnellistefano-1.0.0.dist-info/top_level.txt
ReferenceSystem_busnellistefano-1.0.0.dist-info/RECORD
