Metadata-Version: 2.1
Name: ReferenceSystem-busnellistefano
Version: 1.0.0
Summary: Classi utili a definire una serie di sistemi di riferimento ed i morfismi per trasformare le loro coordinate.
Home-page: https://bitbucket.org/StefanoBusnelli/referencesystem/
Author: Busnelli Stefano Antonio
Author-email: busnelli.stefano@gmail.com
License: UNKNOWN
Platform: UNKNOWN
Classifier: Programming Language :: Python :: 3.9
Classifier: License :: OSI Approved :: MIT License
Classifier: Operating System :: OS Independent
Requires-Dist: numpy
